photo_to_dieses/__init__.py
photo_to_dieses/dice/1.png
photo_to_dieses/dice/2.png
photo_to_dieses/dice/3.png
photo_to_dieses/dice/4.png
photo_to_dieses/dice/5.png
photo_to_dieses/dice/6.png
photo_to_dieses/dice_art_with_qt.py
phototodices-0.1.0.dist-info/LICENSE
phototodices-0.1.0.dist-info/METADATA
phototodices-0.1.0.dist-info/WHEEL
phototodices-0.1.0.dist-info/RECORD
